{"cameraMode":{"drawMode":0,"name":"Shaded","section":"Shading Mode"},"sceneLighting":true,"audioPlay":false,"sceneViewState":{"m_AlwaysRefresh":false,"showFog":true,"showSkybox":true,"showFlares":true,"showImageEffects":true,"showParticleSystems":true,"showVisualEffectGraphs":true,"m_FxEnabled":true},"in2DMode":false,"pivot":{"x":13.7035493850708,"y":-4.734848976135254,"z":-3.414655923843384},"rotation":{"x":0.11340350657701493,"y":0.46877315640449526,"z":-0.060752976685762408,"w":0.8739725947380066},"size":21.433332443237306,"orthographic":false}